MANIFEST.in
reporter.py
setup.py
jupyter_gcs_contents_manager.egg-info/PKG-INFO
jupyter_gcs_contents_manager.egg-info/SOURCES.txt
jupyter_gcs_contents_manager.egg-info/dependency_links.txt
jupyter_gcs_contents_manager.egg-info/top_level.txt